llomuscio_package/__init__.py
llomuscio_package-0.0.1.dist-info/LICENSE
llomuscio_package-0.0.1.dist-info/METADATA
llomuscio_package-0.0.1.dist-info/WHEEL
llomuscio_package-0.0.1.dist-info/top_level.txt
llomuscio_package-0.0.1.dist-info/RECORD
