Metadata-Version: 2.1
Name: llomuscio-package
Version: 0.0.1
Summary: My example package
Home-page: https://github.com/Bobbycookie/Package_Lucas
Author: Lucas L
Author-email: lucas@example.com
License: UNKNOWN
Platform: UNKNOWN
Classifier: Programming Language :: Python :: 3
Classifier: License :: OSI Approved :: MIT License
Classifier: Operating System :: OS Independent
Requires-Python: >=3.6
